Metadata-Version: 2.1
Name: pypterodactyl
Version: 1.0.0
Summary: A Python wrapper for Pterodactyl dashboards
Home-page: UNKNOWN
Author: kokofixcomputers
Author-email: koko@kokofixcomputers.stio.studio
License: UNKNOWN
Platform: UNKNOWN
Classifier: Programming Language :: Python :: 3
Classifier: License :: OSI Approved :: MIT License
Classifier: Operating System :: OS Independent
Requires-Python: >=3.6
